odoo8_addon_event_sale_registration_partner_unique-8.0.1.0.0-py2.7-nspkg.pth
odoo_addons/event_sale_registration_partner_unique/__openerp__.py
odoo_addons/event_sale_registration_partner_unique/__init__.py
odoo_addons/event_sale_registration_partner_unique/README.rst
odoo_addons/event_sale_registration_partner_unique/models/sale_order.py
odoo_addons/event_sale_registration_partner_unique/models/__init__.py
odoo_addons/event_sale_registration_partner_unique/models/event.py
odoo_addons/event_sale_registration_partner_unique/i18n/es.po
odoo_addons/event_sale_registration_partner_unique/tests/test_sale_order.py
odoo_addons/event_sale_registration_partner_unique/tests/__init__.py
odoo8_addon_event_sale_registration_partner_unique-8.0.1.0.0.dist-info/top_level.txt
odoo8_addon_event_sale_registration_partner_unique-8.0.1.0.0.dist-info/WHEEL
odoo8_addon_event_sale_registration_partner_unique-8.0.1.0.0.dist-info/RECORD
odoo8_addon_event_sale_registration_partner_unique-8.0.1.0.0.dist-info/metadata.json
odoo8_addon_event_sale_registration_partner_unique-8.0.1.0.0.dist-info/DESCRIPTION.rst
odoo8_addon_event_sale_registration_partner_unique-8.0.1.0.0.dist-info/METADATA
odoo8_addon_event_sale_registration_partner_unique-8.0.1.0.0.dist-info/namespace_packages.txt
